MANIFEST.in
setup.cfg
setup.py
iati/__init__.py
iati/codelists.py
iati/constants.py
iati/data.py
iati/default.py
iati/exceptions.py
iati/resources.py
iati/rulesets.py
iati/schemas.py
iati/utilities.py
iati/validator.py
iati/resources/lib_data/README.md
iati/resources/lib_data/validation_err_codes.yaml
iati/resources/standard/README.md
iati/resources/standard/101/schemas/iati-activities-schema.xsd
iati/resources/standard/101/schemas/iati-common.xsd
iati/resources/standard/101/schemas/iati-organisations-schema.xsd
iati/resources/standard/101/schemas/iati-registry-record-schema.xsd
iati/resources/standard/101/schemas/xml.xsd
iati/resources/standard/102/schemas/iati-activities-schema.xsd
iati/resources/standard/102/schemas/iati-common.xsd
iati/resources/standard/102/schemas/iati-organisations-schema.xsd
iati/resources/standard/102/schemas/iati-registry-record-schema.xsd
iati/resources/standard/102/schemas/xml.xsd
iati/resources/standard/103/schemas/iati-activities-schema.xsd
iati/resources/standard/103/schemas/iati-common.xsd
iati/resources/standard/103/schemas/iati-organisations-schema.xsd
iati/resources/standard/103/schemas/iati-registry-record-schema.xsd
iati/resources/standard/103/schemas/xml.xsd
iati/resources/standard/104/codelist-mapping.xml
iati/resources/standard/104/codelists/ActivityDateType.xml
iati/resources/standard/104/codelists/ActivityScope.xml
iati/resources/standard/104/codelists/ActivityStatus.xml
iati/resources/standard/104/codelists/AidType-category.xml
iati/resources/standard/104/codelists/AidType.xml
iati/resources/standard/104/codelists/AidTypeFlag.xml
iati/resources/standard/104/codelists/BudgetIdentifier.xml
iati/resources/standard/104/codelists/BudgetIdentifierSector-category.xml
iati/resources/standard/104/codelists/BudgetIdentifierSector.xml
iati/resources/standard/104/codelists/BudgetIdentifierVocabulary.xml
iati/resources/standard/104/codelists/BudgetType.xml
iati/resources/standard/104/codelists/CRSChannelCode.xml
iati/resources/test_data/201/ssot-activity-xml-fail/contact-info/01-missing-organisation-narrative.xml
iati/resources/test_data/201/ssot-activity-xml-fail/contact-info/02-missing-department-narrative.xml
iati/resources/test_data/201/ssot-activity-xml-fail/contact-info/03-missing-job-title-narrative.xml
iati/resources/test_data/201/ssot-activity-xml-fail/contact-info/04-missing-person-name-narrative.xml
iati/resources/test_data/201/ssot-activity-xml-fail/contact-info/05-missing-mailing-address-narrative.xml
iati/resources/test_data/201/ssot-activity-xml-fail/contact-info/07-two-organisations.xml
iati/resources/test_data/201/ssot-activity-xml-fail/contact-info/08-two-departments.xml
iati/resources/test_data/201/ssot-activity-xml-fail/contact-info/09-two-person-names.xml
iati/resources/test_data/201/ssot-activity-xml-fail/contact-info/10-two-job-titles.xml
iati/resources/test_data/201/ssot-activity-xml-pass/contact-info/01-contact-info-example.xml
iati/resources/test_data/201/ssot-activity-xml-pass/contact-info/02-two-mailing-addresses.xml
iati/resources/test_data/202/ssot-activity-xml-fail/contact-info/01-missing-organisation-narrative.xml
iati/resources/test_data/202/ssot-activity-xml-fail/contact-info/02-missing-department-narrative.xml
iati/resources/test_data/202/ssot-activity-xml-fail/contact-info/03-missing-job-title-narrative.xml
iati/resources/test_data/202/ssot-activity-xml-fail/contact-info/04-missing-person-name-narrative.xml
iati/resources/test_data/202/ssot-activity-xml-fail/contact-info/05-missing-mailing-address-narrative.xml
iati/resources/test_data/202/ssot-activity-xml-fail/contact-info/07-two-organisations.xml
iati/resources/test_data/202/ssot-activity-xml-fail/contact-info/08-two-departments.xml
iati/resources/test_data/202/ssot-activity-xml-fail/contact-info/09-two-person-names.xml
iati/resources/test_data/202/ssot-activity-xml-fail/contact-info/10-two-job-titles.xml
iati/resources/test_data/202/ssot-activity-xml-pass/contact-info/01-contact-info-example.xml
iati/resources/test_data/202/ssot-activity-xml-pass/contact-info/02-two-mailing-addresses.xml
pyIATI.egg-info/PKG-INFO
pyIATI.egg-info/SOURCES.txt
pyIATI.egg-info/dependency_links.txt
pyIATI.egg-info/requires.txt
pyIATI.egg-info/top_level.txt